LICENSE
MANIFEST.in
README.rst
setup.py
lxml_xpath2_functions.egg-info/PKG-INFO
lxml_xpath2_functions.egg-info/SOURCES.txt
lxml_xpath2_functions.egg-info/dependency_links.txt
lxml_xpath2_functions.egg-info/pbr.json
lxml_xpath2_functions.egg-info/requires.txt
lxml_xpath2_functions.egg-info/top_level.txt
xpath2_functions/__init__.py
xpath2_functions/functions.py
xpath2_functions/tools.py